nxviz/__init__.py
nxviz/annotate.py
nxviz/api.py
nxviz/edges.py
nxviz/encodings.py
nxviz/facet.py
nxviz/geometry.py
nxviz/highlights.py
nxviz/io.py
nxviz/layouts.py
nxviz/lines.py
nxviz/nodes.py
nxviz/plots.py
nxviz/polcart.py
nxviz/utils.py
nxviz/version.py
nxviz-0.7.6.dist-info/METADATA
nxviz-0.7.6.dist-info/WHEEL
nxviz-0.7.6.dist-info/licenses/LICENSE
nxviz-0.7.6.dist-info/RECORD
