Metadata-Version: 2.4
Name: nxviz
Version: 0.7.6
Summary: Graph Visualization Package
Author-email: "Eric J. Ma" <ericmajinglong@gmail.com>
License-File: LICENSE
Keywords: graph,networkx,nxviz,visualization
Classifier: Intended Audience :: Developers
Classifier: License :: OSI Approved :: MIT License
Classifier: Natural Language :: English
Classifier: Programming Language :: Python :: 3
Requires-Dist: matplotlib>=3.3.3
Requires-Dist: more-itertools>=8.6.0
Requires-Dist: networkx>=2.5
Requires-Dist: numpy>=1.19.4
Requires-Dist: palettable>=3.3.0
Requires-Dist: pandas>=1.2.0
Requires-Dist: seaborn>=0.11.1
Requires-Dist: setuptools
Provides-Extra: docs
Requires-Dist: jupyter; extra == 'docs'
Requires-Dist: mkdocs; extra == 'docs'
Requires-Dist: mkdocs-material; extra == 'docs'
Requires-Dist: mknotebooks; extra == 'docs'
Requires-Dist: pycodestyle; extra == 'docs'
Requires-Dist: pyprojroot; extra == 'docs'
Requires-Dist: sphinx; extra == 'docs'
Provides-Extra: tests
Requires-Dist: hypothesis; extra == 'tests'
Requires-Dist: pre-commit; extra == 'tests'
Requires-Dist: pylint; extra == 'tests'
Requires-Dist: pytest; extra == 'tests'
Requires-Dist: pytest-cov; extra == 'tests'
